stylemod/__init__.py
stylemod/__main__.py
stylemod/cli.py
stylemod/stylemod.py
stylemod/utils.py
stylemod/core/abstract.py
stylemod/core/base.py
stylemod/core/cnn.py
stylemod/core/factory.py
stylemod/core/transformer.py
stylemod/models/__init__.py
stylemod/models/convnext.py
stylemod/models/densenet121.py
stylemod/models/efficientnet_b0.py
stylemod/models/efficientnet_v2_s.py
stylemod/models/regnet_y_16gf.py
stylemod/models/resnet50.py
stylemod/models/swin_t.py
stylemod/models/vgg19.py
stylemod/models/vgg19_eot.py
stylemod/models/vit_b_16.py
stylemod/visualization/architecture.py
stylemod/visualization/gv.py
stylemod/visualization/loss.py
stylemod/visualization/module.py
stylemod/visualization/style.py
stylemod-0.9.1.dist-info/METADATA
stylemod-0.9.1.dist-info/WHEEL
stylemod-0.9.1.dist-info/entry_points.txt
stylemod-0.9.1.dist-info/licenses/LICENSE
stylemod-0.9.1.dist-info/RECORD
