Metadata-Version: 2.3
Name: stylemod
Version: 0.9.1
Summary: Modular neural style transfer library supporting CNN and Transformer-based architectures.
Project-URL: Homepage, https://github.com/ooojustin/stylemod
Project-URL: Documentation, https://github.com/ooojustin/stylemod#readme
Project-URL: Source, https://github.com/ooojustin/stylemod
Project-URL: Tracker, https://github.com/ooojustin/stylemod/issues
Author-email: Justin Garofolo <justin@garofolo.net>
License: MIT
License-File: LICENSE
Classifier: Development Status :: 4 - Beta
Classifier: Intended Audience :: Developers
Classifier: Intended Audience :: Education
Classifier: Intended Audience :: Science/Research
Classifier: License :: OSI Approved :: MIT License
Classifier: Programming Language :: Python :: 3.8
Classifier: Programming Language :: Python :: 3.9
Classifier: Programming Language :: Python :: 3.10
Classifier: Programming Language :: Python :: 3.11
Classifier: Topic :: Scientific/Engineering :: Artificial Intelligence
Classifier: Typing :: Typed
Requires-Python: >=3.8
Requires-Dist: graphviz>=0.20.0
Requires-Dist: matplotlib>=3.1.0
Requires-Dist: pillow>=8.4.0
Requires-Dist: torch>=1.12.0
Requires-Dist: torchvision>=0.12.0
Requires-Dist: tqdm>=4.62.0
